{
  "name": "HCL Admin",
  "short_name": "HCL Admin",
  "description": "HCL Administration Dashboard",
  "display": "standalone",
  "orientation": "portrait",
  "background_color": "#f3f4f6",
  "theme_color": "#4f46e5",
  "icons": [
    {
      "src": "/admin-icon-192.png",
      "sizes": "192x192 512x512 1024x1024",
      "type": "image/png",
      "purpose": "any maskable"
    },
    {
      "src": "/admin-icon-512.png",
      "sizes": "192x192 512x512 1024x1024",
      "type": "image/png",
      "purpose": "any maskable"
    }
  ],
  "id": "/?app=admin"
}